Metadata-Version: 1.1
Name: behest
Version: 0.0.2
Summary: A testing focused opinionated wrapper for requests.
Home-page: UNKNOWN
Author: dwalleck and jidar
Author-email: core.machinarum@gmail.com
License: UNKNOWN
Platform: UNKNOWN
Classifier: Development Status :: 4 - Beta
Classifier: Intended Audience :: Developers
Classifier: Natural Language :: English
Classifier: License :: Other/Proprietary License
Classifier: Operating System :: POSIX :: Linux
Classifier: Programming Language :: Python
Classifier: Programming Language :: Python :: 2.7
